[
  {
    "game_id": 220091358,
    "sig": "f060cf8b5308e392a7bf91e22bfb4b9263fdca9b",
    "url": "https://aoe4world.com/players/8354416-EL-loueMT/games/220091358?sig=f060cf8b5308e392a7bf91e22bfb4b9263fdca9b",
    "map": "Dry Arabia",
    "duration": 1724,
    "result": "win",
    "rating": 2366,
    "player_id": 8354416
  },
  {
    "game_id": 220696790,
    "sig": "d89b60ba937ba7669249aad2911ead7493e1187c",
    "url": "https://aoe4world.com/players/11018483-\u71d5\u5b50\u5b87/games/220696790?sig=d89b60ba937ba7669249aad2911ead7493e1187c",
    "map": "Dry Arabia",
    "duration": 1900,
    "result": "loss",
    "rating": 2205,
    "player_id": 11018483
  },
  {
    "game_id": 220294365,
    "sig": "bdbc6125bce48240de89056ed73d2c79fdae0f25",
    "url": "https://aoe4world.com/players/11018483-\u71d5\u5b50\u5b87/games/220294365?sig=bdbc6125bce48240de89056ed73d2c79fdae0f25",
    "map": "Dry Arabia",
    "duration": 1194,
    "result": "loss",
    "rating": 2203,
    "player_id": 11018483
  },
  {
    "game_id": 220293714,
    "sig": "c3fb9e53d5d3b4b1fe4ea62907b49c9aa51b7fa8",
    "url": "https://aoe4world.com/players/11018483-\u71d5\u5b50\u5b87/games/220293714?sig=c3fb9e53d5d3b4b1fe4ea62907b49c9aa51b7fa8",
    "map": "Dry Arabia",
    "duration": 112,
    "result": "win",
    "rating": 2200,
    "player_id": 11018483
  },
  {
    "game_id": 219670864,
    "sig": "9a7208c72ddfc17d10a83cb1049ac7b5e945ae2b",
    "url": "https://aoe4world.com/players/11018483-\u71d5\u5b50\u5b87/games/219670864?sig=9a7208c72ddfc17d10a83cb1049ac7b5e945ae2b",
    "map": "Dry Arabia",
    "duration": 1493,
    "result": "loss",
    "rating": 2195,
    "player_id": 11018483
  },
  {
    "game_id": 220694062,
    "sig": "cf97a9178e4449e6f653fc063386ce47a3277562",
    "url": "https://aoe4world.com/players/11018483-\u71d5\u5b50\u5b87/games/220694062?sig=cf97a9178e4449e6f653fc063386ce47a3277562",
    "map": "Dry Arabia",
    "duration": 1956,
    "result": "win",
    "rating": 2192,
    "player_id": 11018483
  },
  {
    "game_id": 219670380,
    "sig": "ad4167d03cebcc0a9ce8978a1516d5d3e14020e3",
    "url": "https://aoe4world.com/players/11018483-\u71d5\u5b50\u5b87/games/219670380?sig=ad4167d03cebcc0a9ce8978a1516d5d3e14020e3",
    "map": "Dry Arabia",
    "duration": 155,
    "result": "win",
    "rating": 2192,
    "player_id": 11018483
  },
  {
    "game_id": 220671292,
    "sig": "b1b5dae842ef9e3468a845dd529c7250916dd76b",
    "url": "https://aoe4world.com/players/11018483-\u71d5\u5b50\u5b87/games/220671292?sig=b1b5dae842ef9e3468a845dd529c7250916dd76b",
    "map": "Dry Arabia",
    "duration": 236,
    "result": "win",
    "rating": 2185,
    "player_id": 11018483
  },
  {
    "game_id": 220297438,
    "sig": "95289cf35eb29bb5318eb9f1352ece2a5cd7b5a2",
    "url": "https://aoe4world.com/players/11018483-\u71d5\u5b50\u5b87/games/220297438?sig=95289cf35eb29bb5318eb9f1352ece2a5cd7b5a2",
    "map": "High View",
    "duration": 1801,
    "result": "loss",
    "rating": 2181,
    "player_id": 11018483
  },
  {
    "game_id": 220529533,
    "sig": "4cb8bbabbc2d84036a2bce409ae54d97d89aa707",
    "url": "https://aoe4world.com/players/11018483-\u71d5\u5b50\u5b87/games/220529533?sig=4cb8bbabbc2d84036a2bce409ae54d97d89aa707",
    "map": "Rocky River",
    "duration": 1625,
    "result": "win",
    "rating": 2180,
    "player_id": 11018483
  },
  {
    "game_id": 219570102,
    "sig": "23e2d4e20d968e44f3ffa3351364d56291f2ac4d",
    "url": "https://aoe4world.com/players/11018483-\u71d5\u5b50\u5b87/games/219570102?sig=23e2d4e20d968e44f3ffa3351364d56291f2ac4d",
    "map": "Cliffside",
    "duration": 582,
    "result": "win",
    "rating": 2180,
    "player_id": 11018483
  },
  {
    "game_id": 220731242,
    "sig": "9b7c774286e35f941c073fb5bcdac355e67c6a65",
    "url": "https://aoe4world.com/players/11018483-\u71d5\u5b50\u5b87/games/220731242?sig=9b7c774286e35f941c073fb5bcdac355e67c6a65",
    "map": "Cliffside",
    "duration": 2091,
    "result": "win",
    "rating": 2176,
    "player_id": 11018483
  },
  {
    "game_id": 220228829,
    "sig": "1eea08693afe91f04f09a9ab31d7eb76fac8d7ff",
    "url": "https://aoe4world.com/players/11018483-\u71d5\u5b50\u5b87/games/220228829?sig=1eea08693afe91f04f09a9ab31d7eb76fac8d7ff",
    "map": "High View",
    "duration": 761,
    "result": "loss",
    "rating": 2172,
    "player_id": 11018483
  },
  {
    "game_id": 219673140,
    "sig": "46dd503f7d3a1fc71dc2ad14ec76e2d25363d84b",
    "url": "https://aoe4world.com/players/11018483-\u71d5\u5b50\u5b87/games/219673140?sig=46dd503f7d3a1fc71dc2ad14ec76e2d25363d84b",
    "map": "Gorge",
    "duration": 1537,
    "result": "loss",
    "rating": 2164,
    "player_id": 11018483
  },
  {
    "game_id": 220523135,
    "sig": "eedf15ef8f9c12273d4bbcc20d0ec24717f876fe",
    "url": "https://aoe4world.com/players/11018483-\u71d5\u5b50\u5b87/games/220523135?sig=eedf15ef8f9c12273d4bbcc20d0ec24717f876fe",
    "map": "Socotra",
    "duration": 436,
    "result": "win",
    "rating": 2163,
    "player_id": 11018483
  },
  {
    "game_id": 219943716,
    "sig": "6f5a3c52abc0f7675e240be19316d92b1e24f00d",
    "url": "https://aoe4world.com/players/11018483-\u71d5\u5b50\u5b87/games/219943716?sig=6f5a3c52abc0f7675e240be19316d92b1e24f00d",
    "map": "Rocky River",
    "duration": 947,
    "result": "win",
    "rating": 2142,
    "player_id": 11018483
  },
  {
    "game_id": 219953349,
    "sig": "0f472eef573b4ec82b0a5353b4c38c6f3ffa3ba2",
    "url": "https://aoe4world.com/players/11018483-\u71d5\u5b50\u5b87/games/219953349?sig=0f472eef573b4ec82b0a5353b4c38c6f3ffa3ba2",
    "map": "Gorge",
    "duration": 2168,
    "result": "win",
    "rating": 2135,
    "player_id": 11018483
  },
  {
    "game_id": 219952604,
    "sig": "9e3a96f6f97465de2b3c074fd585707d832a5c55",
    "url": "https://aoe4world.com/players/11018483-\u71d5\u5b50\u5b87/games/219952604?sig=9e3a96f6f97465de2b3c074fd585707d832a5c55",
    "map": "High View",
    "duration": 119,
    "result": "win",
    "rating": 2126,
    "player_id": 11018483
  },
  {
    "game_id": 219949704,
    "sig": "5a9f5d717a128403b1299c7615311daec333d7ba",
    "url": "https://aoe4world.com/players/11018483-\u71d5\u5b50\u5b87/games/219949704?sig=5a9f5d717a128403b1299c7615311daec333d7ba",
    "map": "Socotra",
    "duration": 46,
    "result": "win",
    "rating": 2110,
    "player_id": 11018483
  }
]